xfftspy/__init__.py
xfftspy/data_consumer.py
xfftspy/udp_client.py
xfftspy/util.py
xfftspy-0.1.3.dist-info/LICENSE
xfftspy-0.1.3.dist-info/METADATA
xfftspy-0.1.3.dist-info/WHEEL
xfftspy-0.1.3.dist-info/top_level.txt
xfftspy-0.1.3.dist-info/RECORD
