Metadata-Version: 2.1
Name: xfftspy
Version: 0.1.3
Home-page: https://github.com/ogawa-ros/xfftspy
Author: Nishimura, Atsushi
Author-email: ars096@gmail.com
License: MIT
Classifier: Operating System :: POSIX :: Linux
Classifier: Operating System :: MacOS :: MacOS X
Classifier: Programming Language :: Python
Classifier: Programming Language :: Python :: 3
Classifier: License :: OSI Approved :: MIT License
License-File: LICENSE
